guillotina_elasticsearch/__init__.py
guillotina_elasticsearch/directives.py
guillotina_elasticsearch/events.py
guillotina_elasticsearch/exceptions.py
guillotina_elasticsearch/interfaces.py
guillotina_elasticsearch/manager.py
guillotina_elasticsearch/migration.py
guillotina_elasticsearch/parser.py
guillotina_elasticsearch/py.typed
guillotina_elasticsearch/queries.py
guillotina_elasticsearch/reindex.py
guillotina_elasticsearch/schema.py
guillotina_elasticsearch/testing.py
guillotina_elasticsearch/utility.py
guillotina_elasticsearch/utils.py
guillotina_elasticsearch/commands/__init__.py
guillotina_elasticsearch/commands/fields.py
guillotina_elasticsearch/commands/migrate.py
guillotina_elasticsearch/commands/reindex.py
guillotina_elasticsearch/commands/vacuum.py
guillotina_elasticsearch/tests/_test_flaky.py
guillotina_elasticsearch/tests/conftest.py
guillotina_elasticsearch/tests/fixtures.py
guillotina_elasticsearch/tests/test_catalog.py
guillotina_elasticsearch/tests/test_indexer.py
guillotina_elasticsearch/tests/test_migration.py
guillotina_elasticsearch/tests/test_package.py
guillotina_elasticsearch/tests/test_parser.py
guillotina_elasticsearch/tests/test_schema.py
guillotina_elasticsearch/tests/test_search.py
guillotina_elasticsearch/tests/test_vacuum.py
guillotina_elasticsearch/tests/utils.py
guillotina_elasticsearch-8.0.16.dist-info/licenses/LICENSE
guillotina_elasticsearch-8.0.16.dist-info/METADATA
guillotina_elasticsearch-8.0.16.dist-info/WHEEL
guillotina_elasticsearch-8.0.16.dist-info/top_level.txt
guillotina_elasticsearch-8.0.16.dist-info/zip-safe
guillotina_elasticsearch-8.0.16.dist-info/RECORD
