Metadata-Version: 2.4
Name: guillotina_elasticsearch
Version: 8.0.16
Summary: elasticsearch catalog support for guillotina
Home-page: https://github.com/plone/guillotina_elasticsearch
Author: Ramon Navarro Bosch & Nathan Van Gheem
Author-email: ramon@plone.org
License: GPL version 3
Keywords: search async guillotina elasticsearch
Classifier: Programming Language :: Python :: 3.7
Classifier: Programming Language :: Python :: 3.8
Classifier: Topic :: Software Development :: Libraries :: Python Modules
License-File: LICENSE
Requires-Dist: guillotina>=6.0.0a16
Requires-Dist: elasticsearch[async]<=8.12.0,>=8.0.0
Requires-Dist: mypy_extensions
Requires-Dist: lru-dict
Requires-Dist: backoff
Provides-Extra: test
Requires-Dist: async_asgi_testclient; extra == "test"
Requires-Dist: pytest>=5.0; extra == "test"
Requires-Dist: pytest-asyncio==0.18.3; extra == "test"
Requires-Dist: coverage; extra == "test"
Requires-Dist: pytest-cov; extra == "test"
Requires-Dist: pytest-docker-fixtures[pg]>=1.3.0; extra == "test"
Requires-Dist: prometheus-client>=0.9.0; extra == "test"
Requires-Dist: docker>=7.1.0; extra == "test"
Dynamic: author
Dynamic: author-email
Dynamic: classifier
Dynamic: description
Dynamic: home-page
Dynamic: keywords
Dynamic: license
Dynamic: license-file
Dynamic: provides-extra
Dynamic: requires-dist
Dynamic: summary
